upto/__init__.py
upto/compose_router.py
upto/ichunk.py
upto/pydantic_tools/curry_model.py
upto/pydantic_tools/model_constructors.py
upto/pydantic_tools/mutual_constraint_validator.py
upto-0.1.1.dist-info/METADATA
upto-0.1.1.dist-info/WHEEL
upto-0.1.1.dist-info/RECORD
