Metadata-Version: 2.4
Name: upto
Version: 0.1.1
Author-email: Lukas Plank <lupl@tuta.io>
Requires-Python: ~=3.12
Requires-Dist: pydantic<3,>=2.8.2
Requires-Dist: toolz<0.13,>=0.12.1
